{
  "level": 15,
  "words": [
    {"word": "comprehensive", "pos": "adj", "meanings": ["포괄적인", "종합적인", "광범위한"], "example": "The report provides a comprehensive analysis of the market.", "exampleKo": "그 보고서는 시장에 대한 종합적인 분석을 제공한다.","emoji": ""},
    {"word": "deliberate", "pos": "adj", "meanings": ["고의적인", "의도적인", "신중한"], "example": "It was a deliberate attempt to mislead the public.", "exampleKo": "그것은 대중을 오도하려는 고의적인 시도였다.","emoji": ""},
    {"word": "substitute", "pos": "v", "meanings": ["대체하다", "대신하다"], "example": "You can substitute honey for sugar in this recipe.", "exampleKo": "이 조리법에서는 설탕 대신 꿀을 사용할 수 있다.","emoji": "🔄"},
    {"word": "alleviate", "pos": "v", "meanings": ["완화하다", "덜어 주다", "경감하다"], "example": "The medicine helped alleviate her headache.", "exampleKo": "그 약은 그녀의 두통을 완화하는 데 도움이 되었다.","emoji": ""},
    {"word": "arbitrary", "pos": "adj", "meanings": ["임의적인", "제멋대로인", "자의적인"], "example": "The decision seemed arbitrary and unfair to the students.", "exampleKo": "그 결정은 학생들에게 임의적이고 불공평해 보였다.","emoji": ""},
    {"word": "articulate", "pos": "v", "meanings": ["분명히 표현하다", "또렷이 말하다"], "example": "She articulated her opinion clearly during the debate.", "exampleKo": "그녀는 토론 중에 자신의 의견을 분명히 표현했다.","emoji": "🗣️"},
    {"word": "coincide", "pos": "v", "meanings": ["동시에 일어나다", "일치하다"], "example": "The festival coincides with the national holiday.", "exampleKo": "그 축제는 국경일과 겹친다.","emoji": ""},
    {"word": "coherent", "pos": "adj", "meanings": ["일관성 있는", "조리 있는"], "example": "The essay lacks a coherent argument.", "exampleKo": "그 에세이는 일관성 있는 논거가 부족하다.","emoji": ""},
    {"word": "compatible", "pos": "adj", "meanings": ["호환되는", "양립할 수 있는", "잘 맞는"], "example": "The software is compatible with most operating systems.", "exampleKo": "그 소프트웨어는 대부분의 운영 체제와 호환된다.","emoji": ""},
    {"word": "complement", "pos": "v", "meanings": ["보완하다", "덧붙이다"], "example": "The wine perfectly complements the dish.", "exampleKo": "그 와인은 요리를 완벽하게 보완한다.","emoji": ""},
    {"word": "comprise", "pos": "v", "meanings": ["구성되다", "차지하다", "포함하다"], "example": "The exam comprises three sections.", "exampleKo": "그 시험은 세 부분으로 구성된다.","emoji": ""},
    {"word": "conform", "pos": "v", "meanings": ["따르다", "순응하다", "부합하다"], "example": "All products must conform to safety standards.", "exampleKo": "모든 제품은 안전 기준에 부합해야 한다.","emoji": ""},
    {"word": "contemplate", "pos": "v", "meanings": ["숙고하다", "고려하다", "응시하다"], "example": "He contemplated changing his career.", "exampleKo": "그는 직업을 바꾸는 것을 숙고했다.","emoji": "🤔"},
    {"word": "contend", "pos": "v", "meanings": ["주장하다", "다투다", "겨루다"], "example": "Critics contend that the policy will harm the economy.", "exampleKo": "비평가들은 그 정책이 경제에 해를 끼칠 것이라고 주장한다.","emoji": ""},
    {"word": "conversely", "pos": "adv", "meanings": ["반대로", "역으로"], "example": "Some people work best at night; conversely, others prefer mornings.", "exampleKo": "어떤 사람들은 밤에 일이 가장 잘 되고, 반대로 어떤 사람들은 아침을 선호한다.","emoji": ""},
    {"word": "counterpart", "pos": "n", "meanings": ["상대", "대응 관계에 있는 것", "상대방"], "example": "The Korean minister met with his French counterpart.", "exampleKo": "한국 장관은 프랑스 측 상대와 만났다.","emoji": ""},
    {"word": "deduce", "pos": "v", "meanings": ["추론하다", "연역하다", "알아내다"], "example": "From the footprints, we can deduce the animal's size.", "exampleKo": "발자국을 통해 우리는 그 동물의 크기를 추론할 수 있다.","emoji": "🕵️"},
    {"word": "depict", "pos": "v", "meanings": ["묘사하다", "그리다"], "example": "The painting depicts a peaceful village scene.", "exampleKo": "그 그림은 평화로운 마을 풍경을 묘사한다.","emoji": "🎨"},
    {"word": "designate", "pos": "v", "meanings": ["지정하다", "지명하다", "표시하다"], "example": "The area was designated as a national park.", "exampleKo": "그 지역은 국립 공원으로 지정되었다.","emoji": ""},
    {"word": "deteriorate", "pos": "v", "meanings": ["악화되다", "나빠지다"], "example": "His health deteriorated rapidly after the accident.", "exampleKo": "사고 후 그의 건강은 급속히 악화되었다.","emoji": "📉"},
    {"word": "deviate", "pos": "v", "meanings": ["벗어나다", "일탈하다"], "example": "The plane deviated from its original course.", "exampleKo": "그 비행기는 원래 항로에서 벗어났다.","emoji": ""},
    {"word": "dilemma", "pos": "n", "meanings": ["딜레마", "진퇴양난"], "example": "She faced a dilemma between her career and her family.", "exampleKo": "그녀는 직업과 가족 사이에서 딜레마에 직면했다.","emoji": ""},
    {"word": "disrupt", "pos": "v", "meanings": ["방해하다", "지장을 주다", "붕괴시키다"], "example": "The storm disrupted train services across the region.", "exampleKo": "폭풍이 그 지역 전역의 열차 운행에 지장을 주었다.","emoji": ""},
    {"word": "divert", "pos": "v", "meanings": ["방향을 바꾸다", "전환하다", "우회시키다"], "example": "Traffic was diverted because of the road construction.", "exampleKo": "도로 공사 때문에 차량이 우회되었다.","emoji": "🔀"},
    {"word": "elaborate", "pos": "adj", "meanings": ["정교한", "공들인", "복잡한"], "example": "The palace is famous for its elaborate decorations.", "exampleKo": "그 궁전은 정교한 장식으로 유명하다.","emoji": ""},
    {"word": "elicit", "pos": "v", "meanings": ["이끌어 내다", "유도하다"], "example": "The teacher's question elicited various responses.", "exampleKo": "선생님의 질문은 다양한 반응을 이끌어 냈다.","emoji": ""},
    {"word": "embody", "pos": "v", "meanings": ["구현하다", "구체화하다", "상징하다"], "example": "The statue embodies the spirit of freedom.", "exampleKo": "그 조각상은 자유의 정신을 구현한다.","emoji": ""},
    {"word": "empirical", "pos": "adj", "meanings": ["경험적인", "실증적인"], "example": "The theory is supported by empirical evidence.", "exampleKo": "그 이론은 경험적 증거에 의해 뒷받침된다.","emoji": "🔬"},
    {"word": "entail", "pos": "v", "meanings": ["수반하다", "필요로 하다"], "example": "The job entails a great deal of responsibility.", "exampleKo": "그 일은 상당한 책임을 수반한다.","emoji": ""},
    {"word": "explicit", "pos": "adj", "meanings": ["명시적인", "분명한", "노골적인"], "example": "The teacher gave explicit instructions for the assignment.", "exampleKo": "선생님은 과제에 대해 명확한 지시를 내렸다.","emoji": ""},
    {"word": "exert", "pos": "v", "meanings": ["행사하다", "가하다", "발휘하다"], "example": "Peer groups exert a strong influence on teenagers.", "exampleKo": "또래 집단은 십 대들에게 강한 영향력을 행사한다.","emoji": "💪"},
    {"word": "feasible", "pos": "adj", "meanings": ["실현 가능한", "실행할 수 있는"], "example": "The plan is not feasible with our current budget.", "exampleKo": "그 계획은 현재 우리 예산으로는 실현 가능하지 않다.","emoji": ""},
    {"word": "formulate", "pos": "v", "meanings": ["만들어 내다", "공식화하다", "명확히 표현하다"], "example": "Scientists formulated a new theory to explain the data.", "exampleKo": "과학자들은 그 데이터를 설명하기 위해 새로운 이론을 만들어 냈다.","emoji": ""},
    {"word": "hinder", "pos": "v", "meanings": ["방해하다", "저해하다"], "example": "Heavy fog hindered the rescue operation.", "exampleKo": "짙은 안개가 구조 작업을 방해했다.","emoji": "🚧"},
    {"word": "implicit", "pos": "adj", "meanings": ["암시적인", "내포된", "절대적인"], "example": "There was an implicit criticism in her comment.", "exampleKo": "그녀의 말에는 암시적인 비판이 담겨 있었다.","emoji": ""},
    {"word": "incorporate", "pos": "v", "meanings": ["포함하다", "통합하다", "편입하다"], "example": "The design incorporates traditional Korean elements.", "exampleKo": "그 디자인은 한국의 전통적인 요소들을 포함한다.","emoji": ""},
    {"word": "indispensable", "pos": "adj", "meanings": ["필수적인", "없어서는 안 될"], "example": "Smartphones have become indispensable in daily life.", "exampleKo": "스마트폰은 일상생활에서 없어서는 안 될 것이 되었다.","emoji": ""},
    {"word": "inhibit", "pos": "v", "meanings": ["억제하다", "방해하다", "저해하다"], "example": "Fear can inhibit a person's ability to learn.", "exampleKo": "두려움은 사람의 학습 능력을 저해할 수 있다.","emoji": "🚫"},
    {"word": "innate", "pos": "adj", "meanings": ["타고난", "선천적인"], "example": "Humans have an innate desire to communicate.", "exampleKo": "인간에게는 의사소통하려는 타고난 욕구가 있다.","emoji": "👶"},
    {"word": "intact", "pos": "adj", "meanings": ["온전한", "손상되지 않은", "그대로인"], "example": "The ancient temple remains intact after centuries.", "exampleKo": "그 고대 사원은 수 세기가 지난 후에도 온전하게 남아 있다.","emoji": ""},
    {"word": "integrity", "pos": "n", "meanings": ["진실성", "청렴", "온전함"], "example": "He is respected for his honesty and integrity.", "exampleKo": "그는 정직함과 청렴함으로 존경받는다.","emoji": ""},
    {"word": "intricate", "pos": "adj", "meanings": ["복잡한", "정교한", "얽히고설킨"], "example": "The carpet has an intricate pattern of flowers.", "exampleKo": "그 카펫에는 복잡한 꽃무늬가 있다.","emoji": "🕸️"},
    {"word": "legitimate", "pos": "adj", "meanings": ["합법적인", "정당한", "타당한"], "example": "She had a legitimate reason for missing the class.", "exampleKo": "그녀에게는 수업에 빠질 정당한 이유가 있었다.","emoji": ""},
    {"word": "mitigate", "pos": "v", "meanings": ["완화하다", "경감시키다"], "example": "Planting trees can mitigate the effects of climate change.", "exampleKo": "나무를 심는 것은 기후 변화의 영향을 완화할 수 있다.","emoji": ""},
    {"word": "novel", "pos": "adj", "meanings": ["새로운", "참신한", "기발한"], "example": "The scientist proposed a novel approach to the problem.", "exampleKo": "그 과학자는 그 문제에 대한 참신한 접근법을 제안했다.","emoji": "💡"},
    {"word": "obscure", "pos": "adj", "meanings": ["모호한", "잘 알려지지 않은", "이해하기 어려운"], "example": "The meaning of the poem remains obscure.", "exampleKo": "그 시의 의미는 여전히 모호하다.","emoji": ""},
    {"word": "offset", "pos": "v", "meanings": ["상쇄하다", "벌충하다"], "example": "The gains in one area offset the losses in another.", "exampleKo": "한 분야의 이익이 다른 분야의 손실을 상쇄했다.","emoji": ""},
    {"word": "paradox", "pos": "n", "meanings": ["역설", "모순"], "example": "It is a paradox that we have more devices but less free time.", "exampleKo": "기기는 더 많아졌는데 여가 시간은 더 줄었다는 것은 역설이다.","emoji": ""},
    {"word": "plausible", "pos": "adj", "meanings": ["그럴듯한", "타당해 보이는"], "example": "His excuse sounded plausible, but it was a lie.", "exampleKo": "그의 변명은 그럴듯하게 들렸지만 거짓말이었다.","emoji": ""},
    {"word": "preliminary", "pos": "adj", "meanings": ["예비의", "준비의", "서두의"], "example": "The preliminary results of the study look promising.", "exampleKo": "그 연구의 예비 결과는 유망해 보인다.","emoji": ""},
    {"word": "presume", "pos": "v", "meanings": ["추정하다", "간주하다", "여기다"], "example": "A person is presumed innocent until proven guilty.", "exampleKo": "사람은 유죄가 입증될 때까지 무죄로 추정된다.","emoji": ""},
    {"word": "prevail", "pos": "v", "meanings": ["만연하다", "우세하다", "승리하다"], "example": "Justice will prevail in the end.", "exampleKo": "결국에는 정의가 승리할 것이다.","emoji": ""},
    {"word": "reconcile", "pos": "v", "meanings": ["화해시키다", "조화시키다", "받아들이다"], "example": "It is hard to reconcile economic growth with environmental protection.", "exampleKo": "경제 성장과 환경 보호를 조화시키기는 어렵다.","emoji": "🤝"},
    {"word": "render", "pos": "v", "meanings": ["~하게 만들다", "제공하다", "표현하다"], "example": "The storm rendered the roads impassable.", "exampleKo": "폭풍은 도로를 통행할 수 없게 만들었다.","emoji": ""},
    {"word": "retrieve", "pos": "v", "meanings": ["되찾다", "회수하다", "검색하다"], "example": "The dog was trained to retrieve the ball.", "exampleKo": "그 개는 공을 물어 오도록 훈련받았다.","emoji": "🔍"},
    {"word": "simultaneous", "pos": "adj", "meanings": ["동시의", "동시에 일어나는"], "example": "The event was broadcast with simultaneous interpretation.", "exampleKo": "그 행사는 동시통역과 함께 방송되었다.","emoji": "⏰"},
    {"word": "speculate", "pos": "v", "meanings": ["추측하다", "짐작하다", "투기하다"], "example": "Experts speculate that prices will rise next year.", "exampleKo": "전문가들은 내년에 물가가 오를 것이라고 추측한다.","emoji": ""},
    {"word": "subsequent", "pos": "adj", "meanings": ["그 후의", "이어지는", "다음의"], "example": "The subsequent events proved her prediction right.", "exampleKo": "그 후의 사건들은 그녀의 예측이 옳았음을 증명했다.","emoji": ""},
    {"word": "undermine", "pos": "v", "meanings": ["약화시키다", "훼손하다", "손상시키다"], "example": "Constant criticism can undermine a child's confidence.", "exampleKo": "끊임없는 비판은 아이의 자신감을 약화시킬 수 있다.","emoji": ""},
    {"word": "verify", "pos": "v", "meanings": ["확인하다", "검증하다", "입증하다"], "example": "Always verify information before sharing it online.", "exampleKo": "온라인에 공유하기 전에 항상 정보를 검증하라.","emoji": "✅"}
  ]
}
