{
  "level": 8,
  "words": [
    {"word": "communicate", "pos": "v", "meanings": ["의사소통하다","소통하다"], "example": "We communicate with friends through messages.", "exampleKo": "우리는 메시지로 친구들과 소통한다.", "emoji": "💬"},
    {"word": "achieve", "pos": "v", "meanings": ["성취하다","달성하다"], "example": "She achieved her goal of winning the contest.", "exampleKo": "그녀는 대회에서 우승하겠다는 목표를 달성했다.", "emoji": "🏆"},
    {"word": "admit", "pos": "v", "meanings": ["인정하다","받아들이다"], "example": "He admitted that he was wrong.", "exampleKo": "그는 자신이 틀렸다는 것을 인정했다.", "emoji": "🙋"},
    {"word": "appreciate", "pos": "v", "meanings": ["고마워하다","감상하다","높이 평가하다"], "example": "I really appreciate your help.", "exampleKo": "네 도움에 정말 감사한다.", "emoji": "🙏"},
    {"word": "argue", "pos": "v", "meanings": ["말다툼하다","주장하다"], "example": "The two boys argued about the game.", "exampleKo": "두 소년은 그 게임에 대해 말다툼을 했다.", "emoji": "🗯️"},
    {"word": "attract", "pos": "v", "meanings": ["끌어당기다","매혹하다"], "example": "Flowers attract bees.", "exampleKo": "꽃은 벌을 끌어당긴다.", "emoji": "🧲"},
    {"word": "behave", "pos": "v", "meanings": ["행동하다","예의 바르게 굴다"], "example": "Please behave well at the museum.", "exampleKo": "박물관에서는 바르게 행동해 주세요.", "emoji": ""},
    {"word": "belong", "pos": "v", "meanings": ["속하다","~의 것이다"], "example": "This bag belongs to my sister.", "exampleKo": "이 가방은 내 여동생의 것이다.", "emoji": ""},
    {"word": "compete", "pos": "v", "meanings": ["경쟁하다","겨루다"], "example": "Ten teams will compete in the final.", "exampleKo": "열 팀이 결승에서 겨룰 것이다.", "emoji": "🏁"},
    {"word": "concentrate", "pos": "v", "meanings": ["집중하다"], "example": "I can't concentrate because of the noise.", "exampleKo": "소음 때문에 집중할 수가 없다.", "emoji": "🎯"},
    {"word": "consider", "pos": "v", "meanings": ["고려하다","~라고 여기다"], "example": "You should consider other people's feelings.", "exampleKo": "너는 다른 사람들의 감정을 고려해야 한다.", "emoji": "🤔"},
    {"word": "contain", "pos": "v", "meanings": ["포함하다","담고 있다"], "example": "This drink contains too much sugar.", "exampleKo": "이 음료에는 설탕이 너무 많이 들어 있다.", "emoji": "📦"},
    {"word": "depend", "pos": "v", "meanings": ["의존하다","달려 있다"], "example": "Our picnic depends on the weather.", "exampleKo": "우리의 소풍은 날씨에 달려 있다.", "emoji": ""},
    {"word": "earn", "pos": "v", "meanings": ["(돈을) 벌다","얻다"], "example": "He earns money by delivering newspapers.", "exampleKo": "그는 신문을 배달해서 돈을 번다.", "emoji": "💵"},
    {"word": "escape", "pos": "v", "meanings": ["탈출하다","달아나다"], "example": "The bird escaped from its cage.", "exampleKo": "그 새는 새장에서 탈출했다.", "emoji": "🏃"},
    {"word": "exist", "pos": "v", "meanings": ["존재하다"], "example": "Do aliens really exist?", "exampleKo": "외계인은 정말 존재할까?", "emoji": ""},
    {"word": "focus", "pos": "v", "meanings": ["집중하다","초점을 맞추다"], "example": "Focus on your own work.", "exampleKo": "네 자신의 일에 집중해라.", "emoji": "🎯"},
    {"word": "include", "pos": "v", "meanings": ["포함하다"], "example": "The price includes breakfast.", "exampleKo": "그 가격에는 아침 식사가 포함되어 있다.", "emoji": ""},
    {"word": "influence", "pos": "v", "meanings": ["영향을 미치다"], "example": "Friends can influence your habits.", "exampleKo": "친구들은 너의 습관에 영향을 미칠 수 있다.", "emoji": ""},
    {"word": "mention", "pos": "v", "meanings": ["언급하다","말하다"], "example": "She didn't mention the accident.", "exampleKo": "그녀는 그 사고를 언급하지 않았다.", "emoji": "💬"},
    {"word": "notice", "pos": "v", "meanings": ["알아차리다","주목하다"], "example": "I noticed a change in his voice.", "exampleKo": "나는 그의 목소리에서 변화를 알아차렸다.", "emoji": "👀"},
    {"word": "offer", "pos": "v", "meanings": ["제안하다","제공하다"], "example": "He offered me a seat on the bus.", "exampleKo": "그는 버스에서 나에게 자리를 내주었다.", "emoji": "🎁"},
    {"word": "participate", "pos": "v", "meanings": ["참가하다","참여하다"], "example": "Many students participated in the event.", "exampleKo": "많은 학생들이 그 행사에 참가했다.", "emoji": "🙋"},
    {"word": "persuade", "pos": "v", "meanings": ["설득하다"], "example": "I persuaded my dad to buy me a bike.", "exampleKo": "나는 자전거를 사 달라고 아빠를 설득했다.", "emoji": "🗣️"},
    {"word": "prevent", "pos": "v", "meanings": ["막다","예방하다"], "example": "Washing hands prevents disease.", "exampleKo": "손 씻기는 질병을 예방한다.", "emoji": "🚫"},
    {"word": "recognize", "pos": "v", "meanings": ["알아보다","인정하다"], "example": "I didn't recognize him with his new haircut.", "exampleKo": "새로 머리를 자른 그를 나는 알아보지 못했다.", "emoji": "👁️"},
    {"word": "experience", "pos": "n", "meanings": ["경험","체험"], "example": "Traveling gives you valuable experience.", "exampleKo": "여행은 너에게 값진 경험을 준다.", "emoji": "🌟"},
    {"word": "opportunity", "pos": "n", "meanings": ["기회"], "example": "Don't miss this great opportunity.", "exampleKo": "이 좋은 기회를 놓치지 마라.", "emoji": "🚪"},
    {"word": "attention", "pos": "n", "meanings": ["주의","관심","주목"], "example": "Please pay attention to the teacher.", "exampleKo": "선생님 말씀에 주의를 기울여 주세요.", "emoji": "👀"},
    {"word": "attitude", "pos": "n", "meanings": ["태도","자세"], "example": "A positive attitude helps you learn.", "exampleKo": "긍정적인 태도는 배움에 도움이 된다.", "emoji": ""},
    {"word": "audience", "pos": "n", "meanings": ["관객","청중"], "example": "The audience clapped loudly.", "exampleKo": "관객들이 큰 소리로 박수를 쳤다.", "emoji": "👥"},
    {"word": "benefit", "pos": "n", "meanings": ["이익","혜택"], "example": "Exercise has many health benefits.", "exampleKo": "운동은 건강에 많은 이점이 있다.", "emoji": "🎁"},
    {"word": "decision", "pos": "n", "meanings": ["결정","결심"], "example": "It was a difficult decision to make.", "exampleKo": "그것은 내리기 어려운 결정이었다.", "emoji": "🤔"},
    {"word": "direction", "pos": "n", "meanings": ["방향","지시"], "example": "We walked in the wrong direction.", "exampleKo": "우리는 잘못된 방향으로 걸어갔다.", "emoji": "🧭"},
    {"word": "disaster", "pos": "n", "meanings": ["재난","재해","참사"], "example": "The earthquake was a terrible disaster.", "exampleKo": "그 지진은 끔찍한 재난이었다.", "emoji": "🌪️"},
    {"word": "distance", "pos": "n", "meanings": ["거리"], "example": "The distance from home to school is two kilometers.", "exampleKo": "집에서 학교까지의 거리는 2킬로미터이다.", "emoji": "📏"},
    {"word": "effect", "pos": "n", "meanings": ["영향","효과","결과"], "example": "Smartphones have a big effect on our lives.", "exampleKo": "스마트폰은 우리 삶에 큰 영향을 미친다.", "emoji": ""},
    {"word": "generation", "pos": "n", "meanings": ["세대"], "example": "The older generation grew up without the Internet.", "exampleKo": "기성세대는 인터넷 없이 자랐다.", "emoji": "👪"},
    {"word": "harmony", "pos": "n", "meanings": ["조화","화합"], "example": "People of different cultures live in harmony here.", "exampleKo": "이곳에서는 다른 문화의 사람들이 조화롭게 산다.", "emoji": "🤝"},
    {"word": "invention", "pos": "n", "meanings": ["발명","발명품"], "example": "The printing press was a great invention.", "exampleKo": "인쇄기는 위대한 발명품이었다.", "emoji": "💡"},
    {"word": "memory", "pos": "n", "meanings": ["기억","추억","기억력"], "example": "I have happy memories of my childhood.", "exampleKo": "나는 어린 시절의 행복한 추억이 있다.", "emoji": "🧠"},
    {"word": "population", "pos": "n", "meanings": ["인구"], "example": "The population of the city is growing fast.", "exampleKo": "그 도시의 인구는 빠르게 증가하고 있다.", "emoji": "👨‍👩‍👧‍👦"},
    {"word": "pollution", "pos": "n", "meanings": ["오염","공해"], "example": "Air pollution is getting worse in big cities.", "exampleKo": "대도시에서 대기 오염이 점점 심해지고 있다.", "emoji": "🌫️"},
    {"word": "purpose", "pos": "n", "meanings": ["목적","의도"], "example": "What is the purpose of your visit?", "exampleKo": "당신의 방문 목적은 무엇입니까?", "emoji": ""},
    {"word": "situation", "pos": "n", "meanings": ["상황","처지"], "example": "Stay calm in a dangerous situation.", "exampleKo": "위험한 상황에서는 침착함을 유지해라.", "emoji": ""},
    {"word": "tradition", "pos": "n", "meanings": ["전통"], "example": "Eating rice cake soup on New Year's Day is a Korean tradition.", "exampleKo": "설날에 떡국을 먹는 것은 한국의 전통이다.", "emoji": "🎎"},
    {"word": "confident", "pos": "adj", "meanings": ["자신감 있는","확신하는"], "example": "She felt confident before the speech.", "exampleKo": "그녀는 연설 전에 자신감을 느꼈다.", "emoji": "💪"},
    {"word": "creative", "pos": "adj", "meanings": ["창의적인","독창적인"], "example": "He came up with a creative idea.", "exampleKo": "그는 창의적인 아이디어를 생각해 냈다.", "emoji": "🎨"},
    {"word": "effective", "pos": "adj", "meanings": ["효과적인"], "example": "This is an effective way to memorize words.", "exampleKo": "이것은 단어를 암기하는 효과적인 방법이다.", "emoji": ""},
    {"word": "essential", "pos": "adj", "meanings": ["필수적인","본질적인"], "example": "Water is essential for all living things.", "exampleKo": "물은 모든 생물에게 필수적이다.", "emoji": ""},
    {"word": "familiar", "pos": "adj", "meanings": ["익숙한","친숙한"], "example": "His voice sounded familiar to me.", "exampleKo": "그의 목소리는 나에게 익숙하게 들렸다.", "emoji": ""},
    {"word": "harmful", "pos": "adj", "meanings": ["해로운","유해한"], "example": "Too much screen time is harmful to your eyes.", "exampleKo": "너무 긴 화면 사용 시간은 눈에 해롭다.", "emoji": "☣️"},
    {"word": "negative", "pos": "adj", "meanings": ["부정적인","나쁜"], "example": "Try not to have negative thoughts.", "exampleKo": "부정적인 생각을 하지 않으려고 노력해라.", "emoji": "➖"},
    {"word": "positive", "pos": "adj", "meanings": ["긍정적인","확신하는"], "example": "Positive thinking makes life better.", "exampleKo": "긍정적인 생각은 삶을 더 좋게 만든다.", "emoji": "➕"},
    {"word": "responsible", "pos": "adj", "meanings": ["책임이 있는","책임감 있는"], "example": "You are responsible for your own choices.", "exampleKo": "너는 너 자신의 선택에 책임이 있다.", "emoji": ""},
    {"word": "valuable", "pos": "adj", "meanings": ["귀중한","값비싼"], "example": "Time is more valuable than money.", "exampleKo": "시간은 돈보다 더 귀중하다.", "emoji": "💎"},
    {"word": "completely", "pos": "adv", "meanings": ["완전히","전적으로"], "example": "I completely forgot about the meeting.", "exampleKo": "나는 그 모임에 대해 완전히 잊어버렸다.", "emoji": ""},
    {"word": "gradually", "pos": "adv", "meanings": ["점차","서서히"], "example": "The weather is gradually getting warmer.", "exampleKo": "날씨가 점차 따뜻해지고 있다.", "emoji": ""},
    {"word": "recently", "pos": "adv", "meanings": ["최근에"], "example": "I recently started learning the guitar.", "exampleKo": "나는 최근에 기타를 배우기 시작했다.", "emoji": ""},
    {"word": "despite", "pos": "prep", "meanings": ["~에도 불구하고"], "example": "Despite the rain, the game continued.", "exampleKo": "비에도 불구하고 경기는 계속되었다.", "emoji": ""}
  ]
}
